spacedefense/__init__.py
spacedefense/actors.py
spacedefense/common.py
spacedefense/config.py
spacedefense/flight_unit.py
spacedefense/game.py
spacedefense/my_master.py
spacedefense/scene_main.py
spacedefense/scenes.py
spacedefense/assets/.DS_Store
spacedefense/assets/images/.DS_Store
spacedefense/assets/images/game_cover.webp
spacedefense/assets/images/game_cover_loss.webp
spacedefense/assets/images/game_cover_win.webp
spacedefense/assets/images/icon.png
spacedefense/assets/images/my_slave_fighter1.webp
spacedefense/assets/images/my_slave_fighter2.webp
spacedefense/assets/images/scale_cambg1.webp
spacedefense/assets/images/super_bullet.webp
spacedefense/assets/images/ufo_super_bullet.webp
spacedefense/assets/images/myf_master/.DS_Store
spacedefense/assets/images/myf_master/myf_master_001.webp
spacedefense/assets/images/myf_master/myf_master_002.webp
spacedefense/assets/images/myf_master/myf_master_003.webp
spacedefense/assets/images/myf_master/myf_master_004.webp
spacedefense/assets/images/ufo_master/.DS_Store
spacedefense/assets/images/ufo_master/ufo_master_001.webp
spacedefense/assets/images/ufo_master/ufo_master_002.webp
spacedefense/assets/images/ufo_master/ufo_master_003.webp
spacedefense/assets/images/ufo_master/ufo_master_004.webp
spacedefense/assets/images/ufo_slave/.DS_Store
spacedefense/assets/images/ufo_slave/ufo_slave_001.webp
spacedefense/assets/images/ufo_slave/ufo_slave_002.webp
spacedefense/assets/images/ufo_slave/ufo_slave_003.webp
spacedefense/assets/images/ufo_slave/ufo_slave_004.webp
spacedefense/assets/images/vmove_cambg1/.DS_Store
spacedefense/assets/images/vmove_cambg1/cambg_001.webp
spacedefense/assets/images/vmove_cambg1/cambg_002.webp
spacedefense/assets/images/vmove_cambg1/cambg_003.webp
spacedefense/assets/images/vmove_cambg2/.DS_Store
spacedefense/assets/images/vmove_cambg2/cambg_001.webp
spacedefense/assets/images/vmove_cambg2/cambg_002.webp
spacedefense/assets/images/vmove_cambg2/cambg_003.webp
spacedefense/assets/sounds/.DS_Store
SightTraining-0.1.24.dist-info/LICENSE
SightTraining-0.1.24.dist-info/METADATA
SightTraining-0.1.24.dist-info/WHEEL
SightTraining-0.1.24.dist-info/entry_points.txt
SightTraining-0.1.24.dist-info/top_level.txt
SightTraining-0.1.24.dist-info/RECORD
