Metadata-Version: 2.1
Name: SightTraining
Version: 0.1.24
Summary: SightTraining  is a game for children's amblyopia training
Author: jett.wang
Author-email: jamiesun.net@gmail.com
Classifier: Programming Language :: Python :: 3
Classifier: License :: OSI Approved :: MIT License
Classifier: Operating System :: OS Independent
Requires-Python: >=3.10
License-File: LICENSE
Requires-Dist: pygame (==2.5.1)
Requires-Dist: python-dotenv (>=1.0.1)
